setup.py
umeng_push/__init__.py
umeng_push/example.test.py
umeng_push.egg-info/PKG-INFO
umeng_push.egg-info/SOURCES.txt
umeng_push.egg-info/dependency_links.txt
umeng_push.egg-info/not-zip-safe
umeng_push.egg-info/pbr.json
umeng_push.egg-info/top_level.txt
umeng_push/services/__init__.py
umeng_push/services/message/__init__.py
umeng_push/services/message/connect.py
umeng_push/services/message/error_codes.py