Metadata-Version: 1.1
Name: umeng-push
Version: 0.4
Summary: UMeng Push Service Python API
Home-page: UNKNOWN
Author: WANG Tai
Author-email: i@wangtai.me
License: Apache2
Platform: UNKNOWN
Classifier: Development Status :: 4 - Beta
Classifier: Environment :: Web Environment
Classifier: Framework :: Django
Classifier: Intended Audience :: Developers
Classifier: Natural Language :: English
Classifier: Operating System :: POSIX :: Linux
Classifier: Programming Language :: Python
Classifier: Topic :: System :: Installation/Setup
